{
  "project_info": {
    "project_number": "595406356279",
    "project_id": "my-crusade",
    "storage_bucket": "my-crusade.appspot.com"
  },
  "client": [
    {
      "client_info": {
        "mobilesdk_app_id": "1:595406356279:android:bee59ef9cb47a6e2f824b2",
        "android_client_info": {
          "package_name": "com.example.my_crusade"
        }
      },
      "oauth_client": [
        {
          "client_id": "595406356279-mfu9ujjkscs3isiqta0iegpprrhpnk9d.apps.googleusercontent.com",
          "client_type": 3
        }
      ],
      "api_key": [
        {
          "current_key": "AIzaSyCWegeSuddExP_KW0-gjTpWT64dqW2PZc8"
        }
      ],
      "services": {
        "appinvite_service": {
          "other_platform_oauth_client": [
            {
              "client_id": "595406356279-mfu9ujjkscs3isiqta0iegpprrhpnk9d.apps.googleusercontent.com",
              "client_type": 3
            }
          ]
        }
      }
    }
  ],
  "configuration_version": "1"
}